drawing/Edge.py
drawing/Graph.py
drawing/GraphObj.py
drawing/Node.py
drawing/Style.py
drawing/__init__.py
drawing-0.0.3.dist-info/LICENSE
drawing-0.0.3.dist-info/METADATA
drawing-0.0.3.dist-info/WHEEL
drawing-0.0.3.dist-info/top_level.txt
drawing-0.0.3.dist-info/zip-safe
drawing-0.0.3.dist-info/RECORD
