Metadata-Version: 2.1
Name: drawing
Version: 0.0.3
Summary: Python library for creating and manipulating graphs
Home-page: https://github.com/idin/drawing
Author: Idin
Author-email: py@idin.ca
License: MIT
Keywords: graph
Platform: UNKNOWN
Classifier: Development Status :: 3 - Alpha
Classifier: Intended Audience :: Developers
Classifier: License :: OSI Approved :: MIT License
Classifier: Programming Language :: Python :: 3 :: Only
Classifier: Programming Language :: Python :: 3.6
Classifier: Programming Language :: Python :: 3.7
Classifier: Topic :: Software Development :: Libraries :: Python Modules
Requires-Python: ~=3.6
Requires-Dist: graphviz
